<?xml version="1.0" encoding="UTF-8"?>
<objects serializationModel="Studio.02.02.00">
	<object class="AudioFile" id="{af6ef819-ac88-4312-82f1-953bd5aab579}">
		<property name="assetPath">
			<value>SFX/Attack-005.wav</value>
		</property>
		<property name="frequencyInKHz">
			<value>48</value>
		</property>
		<property name="channelCount">
			<value>2</value>
		</property>
		<property name="length">
			<value>1.3918958333333333</value>
		</property>
		<relationship name="masterAssetFolder">
			<destination>{26e0e549-e399-4fd3-801c-853cd22e2f2f}</destination>
		</relationship>
	</object>
</objects>
